{
  "updated_at": "2026-02-26 01:23:30",
  "prices": {
    "000660": {
      "current_price": 1037000,
      "all_time_high": 1053500,
      "all_time_high_date": "2026-02-26",
      "ratio": 98.43
    },
    "028260": {
      "current_price": 352500,
      "all_time_high": 364000,
      "all_time_high_date": "2026-02-26",
      "ratio": 96.84
    },
    "064350": {
      "current_price": 218500,
      "all_time_high": 249500,
      "all_time_high_date": "2025-10-23",
      "ratio": 87.58
    },
    "079550": {
      "current_price": 505000,
      "all_time_high": 650000,
      "all_time_high_date": "2025-06-23",
      "ratio": 77.69
    },
    "140860": {
      "current_price": 279500,
      "all_time_high": 321500,
      "all_time_high_date": "2026-01-29",
      "ratio": 86.94
    },
    "469160": {
      "current_price": 21900,
      "all_time_high": 22985,
      "all_time_high_date": "2026-02-19",
      "ratio": 95.28
    },
    "449450": {
      "current_price": 69320,
      "all_time_high": 71180,
      "all_time_high_date": "2026-02-04",
      "ratio": 97.39
    },
    "411060": {
      "current_price": 33270,
      "all_time_high": 37890,
      "all_time_high_date": "2026-01-29",
      "ratio": 87.81
    },
    "005930": {
      "current_price": 213500,
      "all_time_high": 217500,
      "all_time_high_date": "2026-02-26",
      "ratio": 98.16
    },
    "161510": {
      "current_price": 29040,
      "all_time_high": 30291,
      "all_time_high_date": "2026-02-23",
      "ratio": 95.87
    }
  }
}