{
  "updated_at": "2026-05-07 05:07:45",
  "prices": {
    "000660": {
      "current_price": 1628000,
      "all_time_high": 1648000,
      "all_time_high_date": "2026-05-07",
      "ratio": 98.79
    },
    "028260": {
      "current_price": 386500,
      "all_time_high": 396000,
      "all_time_high_date": "2026-05-07",
      "ratio": 97.6
    },
    "064350": {
      "current_price": 238000,
      "all_time_high": 282000,
      "all_time_high_date": "2026-04-30",
      "ratio": 84.4
    },
    "079550": {
      "current_price": 959000,
      "all_time_high": 1118000,
      "all_time_high_date": "2026-04-22",
      "ratio": 85.78
    },
    "140860": {
      "current_price": 307000,
      "all_time_high": 330000,
      "all_time_high_date": "2026-05-06",
      "ratio": 93.03
    },
    "469160": {
      "current_price": 26230,
      "all_time_high": 27500,
      "all_time_high_date": "2026-05-07",
      "ratio": 95.38
    },
    "449450": {
      "current_price": 76945,
      "all_time_high": 88030,
      "all_time_high_date": "2026-03-04",
      "ratio": 87.41
    },
    "411060": {
      "current_price": 30700,
      "all_time_high": 37890,
      "all_time_high_date": "2026-01-29",
      "ratio": 81.02
    },
    "005930": {
      "current_price": 267250,
      "all_time_high": 277000,
      "all_time_high_date": "2026-05-07",
      "ratio": 96.48
    },
    "161510": {
      "current_price": 27700,
      "all_time_high": 30192,
      "all_time_high_date": "2026-02-23",
      "ratio": 91.75
    }
  }
}